{"expires":1761414480447,"value":{"code":200,"headers":{"etag":"W/\"YmPBbztoBk\"","last-modified":"Sat, 18 Oct 2025 17:48:00 GMT","cache-control":"s-maxage=604800, stale-while-revalidate"},"body":{"prefix":"lucide","icons":{"chevron-down":{"body":"<path fill=\"none\" stroke=\"currentColor\" stroke-linecap=\"round\" stroke-linejoin=\"round\" stroke-width=\"2\" d=\"m6 9l6 6l6-6\"/>"},"circle-user-round":{"body":"<g fill=\"none\" stroke=\"currentColor\" stroke-linecap=\"round\" stroke-linejoin=\"round\" stroke-width=\"2\"><path d=\"M18 20a6 6 0 0 0-12 0\"/><circle cx=\"12\" cy=\"10\" r=\"4\"/><circle cx=\"12\" cy=\"12\" r=\"10\"/></g>"},"instagram":{"body":"<g fill=\"none\" stroke=\"currentColor\" stroke-linecap=\"round\" stroke-linejoin=\"round\" stroke-width=\"2\"><rect width=\"20\" height=\"20\" x=\"2\" y=\"2\" rx=\"5\" ry=\"5\"/><path d=\"M16 11.37A4 4 0 1 1 12.63 8A4 4 0 0 1 16 11.37m1.5-4.87h.01\"/></g>"},"menu":{"body":"<path fill=\"none\" stroke=\"currentColor\" stroke-linecap=\"round\" stroke-linejoin=\"round\" stroke-width=\"2\" d=\"M4 12h16M4 18h16M4 6h16\"/>"},"shopping-cart":{"body":"<g fill=\"none\" stroke=\"currentColor\" stroke-linecap=\"round\" stroke-linejoin=\"round\" stroke-width=\"2\"><circle cx=\"8\" cy=\"21\" r=\"1\"/><circle cx=\"19\" cy=\"21\" r=\"1\"/><path d=\"M2.05 2.05h2l2.66 12.42a2 2 0 0 0 2 1.58h9.78a2 2 0 0 0 1.95-1.57l1.65-7.43H5.12\"/></g>"}},"lastModified":1756357794,"width":24,"height":24}},"mtime":1760809680447,"integrity":"maX4dISsQJ"}